hardware/src/bsram.v
/** @module : BSRAM
 *  @author : Adaptive & Secure Computing Systems (ASCS) Laboratory
 
 *  Copyright (c) 2018 BRISC-V (ASCS/ECE/BU)
 *  Permission is hereby granted, free of charge, to any person obtaining a copy
 *  of this software and associated documentation files (the "Software"), to deal
 *  in the Software without restriction, including without limitation the rights
 *  to use, copy, modify, merge, publish, distribute, sublicense, and/or sell
 *  copies of the Software, and to permit persons to whom the Software is
 *  furnished to do so, subject to the following conditions:
 *  The above copyright notice and this permission notice shall be included in
 *  all copies or substantial portions of the Software.

 *  THE SOFTWARE IS PROVIDED "AS IS", WITHOUT WARRANTY OF ANY KIND, EXPRESS OR
 *  IMPLIED, INCLUDING BUT NOT LIMITED TO THE WARRANTIES OF MERCHANTABILITY,
 *  FITNESS FOR A PARTICULAR PURPOSE AND NONINFRINGEMENT. IN NO EVENT SHALL THE
 *  AUTHORS OR COPYRIGHT HOLDERS BE LIABLE FOR ANY CLAIM, DAMAGES OR OTHER
 *  LIABILITY, WHETHER IN AN ACTION OF CONTRACT, TORT OR OTHERWISE, ARISING FROM,
 *  OUT OF OR IN CONNECTION WITH THE SOFTWARE OR THE USE OR OTHER DEALINGS IN
 *  THE SOFTWARE.
 */
 
//Same cycle read memory access 

 (* ram_style = "block" *)
module BSRAM #(parameter CORE = 0, DATA_WIDTH = 32, ADDR_WIDTH = 8) (
        clock,
        reset,
        readEnable,
        readAddress,
        readData,
        writeEnable,
        writeAddress,
        writeData, 
        report
); 

localparam MEM_DEPTH = 1 << ADDR_WIDTH;

input clock; 
input reset; 
input readEnable;
input [ADDR_WIDTH-1:0]   readAddress;
output [DATA_WIDTH-1:0]  readData;
input writeEnable;
input [ADDR_WIDTH-1:0]   writeAddress;
input [DATA_WIDTH-1:0]   writeData;
input report; 
 
wire [DATA_WIDTH-1:0]     readData;
reg  [DATA_WIDTH-1:0]     sram [0:MEM_DEPTH-1];
 
//--------------Code Starts Here------------------ 
assign readData = (readEnable & writeEnable & (readAddress == writeAddress))? 
                  writeData : readEnable? sram[readAddress] : 0;

initial begin
    $readmemh("program.vmh", sram);
end

always@(posedge clock) begin : RAM_WRITE
    if(writeEnable)
        sram[writeAddress] <= writeData;
end

reg [31: 0] cycles; 
always @ (posedge clock) begin 
    cycles <= reset? 0 : cycles + 1; 
    if (report)begin
        $display ("------ Core %d SBRAM Unit - Current Cycle %d --------", CORE, cycles); 
        $display ("| Read        [%b]", readEnable);
        $display ("| Read Address[%h]", readAddress);
        $display ("| Read Data   [%h]", readData);
        $display ("| Write       [%b]", writeEnable);
        $display ("| Write Addres[%h]", writeAddress);
        $display ("| Write Data  [%h]", writeData);
        $display ("----------------------------------------------------------------------");
    end 
 end    

endmodule

hardware/src/Cache.v
//////////////////////////////////////////////////////////////////////////////////
// 
//	GENERIC DIRECT-MAPPED CACHE MODEL WITH WRITE-THROUGH AND NO-WRITE-ALLOCATE
// 
//////////////////////////////////////////////////////////////////////////////////

// TODO: should have different read and write inputs for consistency?
// TODO: implement lower levels memory search

module Cache #(
	parameter LOG_NUM_LINES = 12,		// number of entries in cache
	parameter LOG_NUM_BLOCKS = 2,		// number of blocks in each cache line
	parameter DATA_WIDTH = 32)(
	input 						clk,
	input 						rst,
	input 						write_en,
	input 	[DATA_WIDTH-1:0]	write_data,
	input 	[LOG_NUM_LINES:0] 	address,
	output						hit,
	output	[DATA_WIDTH-1:0]	read_data
);

	localparam NUM_TAG_BITS = DATA_WIDTH-LOG_NUM_LINES-LOG_NUM_BLOCKS;
	localparam NUM_LINES = 2**LOG_NUM_LINES;
	localparam NUM_BLOCKS = 2**LOG_NUM_BLOCKS;

	// tags of all data in cache
	reg [NUM_TAG_BITS-1:0] tags[0:2**LOG_NUM_LINES];

	// valid bits of all data in cache
	reg valid[0:NUM_LINES-1];
	
	// each cache line is of size (data width) * (num blocks)
	reg [DATA_WIDTH-1:0] cachemem[0:NUM_LINES-1][0:NUM_BLOCKS-1];

	// index, tag, block offset bits in requested address
	wire [NUM_TAG_BITS-1:0] tag = address[31:32-NUM_TAG_BITS];
	wire [LOG_NUM_BLOCKS-1:0] block_offset = address[LOG_NUM_BLOCKS-1:0];
	wire [LOG_NUM_LINES-1:0] index = address[LOG_NUM_LINES+LOG_NUM_BLOCKS-1:LOG_NUM_BLOCKS];

	// does this cache have the requested data
	assign hit = valid[index] && tags[index]==tag;

	// asynchronous read 
	// assign read_data = cachemem[index][NUM_BLOCKS-block_offset-1];

	always @ (posedge clk) begin

		if (write_en) begin
			cachemem[index][NUM_BLOCKS-block_offset-1] = write_data;
		end // if (write_en)

	end // always @ (posedge clk)

endmodule

hardware/src/CacheModel.v
//////////////////////////////////////////////////////////////////////////////////
// 
//	SIMULATES L1,L2 CACHE AND MAIN MEMORY ALL WORKING TOGETHER
// 
//////////////////////////////////////////////////////////////////////////////////

// TODO: i-cache

module CacheModel #(parameter CORE = 0, DATA_WIDTH = 32, ADDR_WIDTH = 8)(
	input 						clk,			// clock
	input 						rst,			// synchronous reset active high
	input 						report,			// report stats active high
	input 						write_en,
	input	[ADDR_WIDTH-1:0]	address,
	input	[DATA_WIDTH-1:0]	write_data,
	output	[DATA_WIDTH-1:0]	read_data
);


///////////////////////////////////// L1 CACHE /////////////////////////////////////
	
	wire 						l1i_hit, l1d_hit;
	wire 	[DATA_WIDTH-1:0]	l1i_write_data, l1d_write_data;
	wire 	[DATA_WIDTH-1:0]	l1i_read_data, l1d_read_data;

	Cache l1icache (
		.clk       (clk),
		.rst       (rst),
		.write_en  (l1i_write_en),
		.write_data(l1i_write_data),
		.address   (address),
		.hit       (l1i_hit),
		.read_data (l1i_read_data)
	);

	Cache l1dcache (
		.clk       (clk),
		.rst       (rst),
		.write_en  (l1d_write_en),
		.write_data(l1d_write_data),
		.address   (address),
		.hit       (l1d_hit),
		.read_data (l1d_read_data)
	);


///////////////////////////////////// L2 CACHE /////////////////////////////////////

	wire 						l2_hit;
	wire 	[DATA_WIDTH-1:0]	l2_write_data;
	wire 	[DATA_WIDTH-1:0]	l2_read_data;

	Cache l2cache (
		.clk       (clk),
		.rst       (rst),
		.write_en  (l2_write_en),
		.write_data(l2_write_data),
		.address   (address),
		.hit       (l2_hit),
		.read_data (l2_read_data)
	);


///////////////////////////////////// MAIN MEMORY /////////////////////////////////////

	wire 						mm_read_en = 1;
	wire 	[DATA_WIDTH-1:0]	mm_read_data;

	BSRAM main_memory (
		.clock       (clk),
		.reset       (rst),
		.readEnable  (mm_read_en),
		.readAddress (address),
		.readData    (mm_read_data),
		.writeEnable (write_en),
		.writeAddress(address),
		.writeData   (write_data),
		.report      (report)
	);


////////////////////////////////////// READS //////////////////////////////////////

	// In this simulation, all caches and mem can be read at the same time but
	// this is not realistic and impossible in real workd
	assign read_data = l1d_hit	?	l1d_read_data
					 : l2_hit	?	l2_read_data
					 : mm_read_data;


///////////////////////////////////// WRITES /////////////////////////////////////

	// write through all levels of memory whenever write requested or read miss
	assign l1d_write_en = (~rst) && (write_en || ~l1d_hit);
	assign l2_write_en = (~rst) && (write_en || ~l2_hit);
	assign mm_write_en = (~rst) && (write_en);

	// in write req, write the input data. in read miss, write data from lower level of memory
	assign l1d_write_data = ~l1d_hit ? ( ~l2_hit ? mm_read_data : l2_read_data)
						  : write_data;

	assign l2_write_data = ~l2_hit ? mm_read_data : write_data;

endmodule

hardware/testbeds/tb_CacheModel.v
module tb_CacheModel;

	// Inputs
	reg 		clk;
	reg 		rst;
	reg 		report;
	reg 		write_en;
	reg	[7:0]	address;
	reg	[31:0]	write_data;

	// Outputs
	wire [31:0] read_data;

	CacheModel uut (
		.clk       (clk),
		.rst       (rst),
		.report    (report),
		.write_en  (write_en),
		.address   (address),
		.write_data(write_data),
		.read_data (read_data)
	);

	// clock generator
	always #1 clk = ~clk;

	initial begin

		$dumpfile("CacheModel.vcd");
		$dumpvars(0, uut, uut.l1dcache.cachemem[0][0], uut.l1dcache.cachemem[0][1],
							uut.l2cache.cachemem[0][0], uut.l2cache.cachemem[0][1],
							uut.l2cache.cachemem[4][0], uut.l2cache.cachemem[4][1],
							uut.l1dcache.tags[0], uut.l1dcache.tags[1],
							uut.l2cache.tags[0], uut.l2cache.tags[1]);

		clk = 1;
		rst = 1;
		report = 0;
		write_en = 0;
		address = 8'h20;
		write_data = 32'habcdef;

		#10 rst = 0;
		// first 2s - miss (cold)
		// next 2s - all hit (same addr)
		
		// next 2s - l1 miss, l2 hit
		// next 2s - all hit (same addr)
		#4 address = 8'h18;

		// missed in both l1 and l2
		// next 2s - all miss (new addr, same cache location)
		// next 2s - all hit (same addr)
		#4 address = 8'h30;
		#2 address = 8'h28;
		// write through all
		#10 write_en = 1;

		#10 write_en = 0;

		#10 rst = 1; 

	    //everything should be reset in the case
		#2
		$finish;

	end // initial

endmodule

hardware/src/CacheModel.vcd
$date
	Thu Apr 19 18:11:58 2018
$end
$version
	Icarus Verilog
$end
$timescale
	1s
$end
$scope module tb_CacheModel $end
$scope module uut $end
$var wire 8 ! address [7:0] $end
$var wire 1 " clk $end
$var wire 1 # l1d_write_en $end
$var wire 32 $ l1i_write_data [31:0] $end
$var wire 1 % l1i_write_en $end
$var wire 1 & l2_write_en $end
$var wire 1 ' mm_read_en $end
$var wire 1 ( mm_write_en $end
$var wire 1 ) report $end
$var wire 1 * rst $end
$var wire 32 + write_data [31:0] $end
$var wire 1 , write_en $end
$var wire 32 - read_data [31:0] $end
$var wire 32 . mm_read_data [31:0] $end
$var wire 32 / l2_write_data [31:0] $end
$var wire 32 0 l2_read_data [31:0] $end
$var wire 1 1 l2_hit $end
$var wire 32 2 l1i_read_data [31:0] $end
$var wire 1 3 l1i_hit $end
$var wire 32 4 l1d_write_data [31:0] $end
$var wire 32 5 l1d_read_data [31:0] $end
$var wire 1 6 l1d_hit $end
$scope module l1dcache $end
$var wire 8 7 address [7:0] $end
$var wire 1 " clk $end
$var wire 1 6 hit $end
$var wire 32 8 read_data [31:0] $end
$var wire 1 * rst $end
$var wire 32 9 write_data [31:0] $end
$var wire 1 # write_en $end
$var wire 5 : tag [4:0] $end
$var wire 2 ; index [1:0] $end
$var wire 1 < block_offset $end
$var reg 4 = valid [3:0] $end
$upscope $end
$scope module l1icache $end
$var wire 8 > address [7:0] $end
$var wire 1 " clk $end
$var wire 1 3 hit $end
$var wire 32 ? read_data [31:0] $end
$var wire 1 * rst $end
$var wire 32 @ write_data [31:0] $end
$var wire 1 % write_en $end
$var wire 5 A tag [4:0] $end
$var wire 2 B index [1:0] $end
$var wire 1 C block_offset $end
$var reg 4 D valid [3:0] $end
$upscope $end
$scope module l2cache $end
$var wire 8 E address [7:0] $end
$var wire 1 " clk $end
$var wire 1 1 hit $end
$var wire 32 F read_data [31:0] $end
$var wire 1 * rst $end
$var wire 32 G write_data [31:0] $end
$var wire 1 & write_en $end
$var wire 4 H tag [3:0] $end
$var wire 3 I index [2:0] $end
$var wire 1 J block_offset $end
$var reg 8 K valid [7:0] $end
$upscope $end
$scope module main_memory $end
$var wire 1 " clock $end
$var wire 8 L readAddress [7:0] $end
$var wire 1 ' readEnable $end
$var wire 1 ) report $end
$var wire 1 * reset $end
$var wire 8 M writeAddress [7:0] $end
$var wire 32 N writeData [31:0] $end
$var wire 1 , writeEnable $end
$var wire 32 O readData [31:0] $end
$var reg 32 P cycles [31:0] $end
$scope begin RAM_WRITE $end
$upscope $end
$upscope $end
$upscope $end
$upscope $end
$scope module tb_CacheModel $end
$scope module uut $end
$scope module l1dcache $end
$var reg 32 Q \cachemem[0] [31:0] $end
$upscope $end
$upscope $end
$upscope $end
$scope module tb_CacheModel $end
$scope module uut $end
$scope module l1dcache $end
$var reg 32 R \cachemem[1] [31:0] $end
$upscope $end
$upscope $end
$upscope $end
$scope module tb_CacheModel $end
$scope module uut $end
$scope module l2cache $end
$var reg 32 S \cachemem[0] [31:0] $end
$upscope $end
$upscope $end
$upscope $end
$scope module tb_CacheModel $end
$scope module uut $end
$scope module l2cache $end
$var reg 32 T \cachemem[1] [31:0] $end
$upscope $end
$upscope $end
$upscope $end
$scope module tb_CacheModel $end
$scope module uut $end
$scope module l2cache $end
$var reg 32 U \cachemem[8] [31:0] $end
$upscope $end
$upscope $end
$upscope $end
$scope module tb_CacheModel $end
$scope module uut $end
$scope module l2cache $end
$var reg 32 V \cachemem[9] [31:0] $end
$upscope $end
$upscope $end
$upscope $end
$scope module tb_CacheModel $end
$scope module uut $end
$scope module l1dcache $end
$var reg 5 W \tags[0] [4:0] $end
$upscope $end
$upscope $end
$upscope $end
$scope module tb_CacheModel $end
$scope module uut $end
$scope module l1dcache $end
$var reg 5 X \tags[1] [4:0] $end
$upscope $end
$upscope $end
$upscope $end
$scope module tb_CacheModel $end
$scope module uut $end
$scope module l2cache $end
$var reg 4 Y \tags[0] [3:0] $end
$upscope $end
$upscope $end
$upscope $end
$scope module tb_CacheModel $end
$scope module uut $end
$scope module l2cache $end
$var reg 4 Z \tags[1] [3:0] $end
$upscope $end
$upscope $end
$upscope $end
$enddefinitions $end
#0
$dumpvars
bx Z
bx Y
bx X
bx W
bx V
bx U
bx T
bx S
bx R
bx Q
b0 P
b111010010011 O
b101010111100110111101111 N
b100000 M
b100000 L
b0 K
0J
b0 I
b10 H
b111010010011 G
bx F
b100000 E
b0 D
0C
b0 B
b100 A
bz @
bx ?
b100000 >
b0 =
0<
b0 ;
b100 :
b111010010011 9
bx 8
b100000 7
06
bx 5
b111010010011 4
03
bx 2
01
bx 0
b111010010011 /
b111010010011 .
b111010010011 -
0,
b101010111100110111101111 +
1*
0)
0(
1'
0&
z%
bz $
0#
1"
b100000 !
$end
#1
0"
#2
1"
#3
0"
#4
1"
#5
0"
#6
1"
#7
0"
#8
1"
#9
0"
#10
b1 P
1#
1&
1"
0*
#11
0"
#12
0#
0&
b101010111100110111101111 4
b101010111100110111101111 9
b101010111100110111101111 /
b101010111100110111101111 G
16
11
b1 =
b100 W
b111010010011 Q
b111010010011 5
b111010010011 8
b1 K
b10 Y
b111010010011 S
b111010010011 0
b111010010011 F
b10 P
1"
#13
0"
#14
b11 P
1#
1&
b101010010011 4
b101010010011 9
b101010010011 /
b101010010011 G
b101010010011 -
06
01
b11 :
b11 A
b1 H
bx 0
bx F
b100 I
b101010010011 .
b101010010011 O
1"
b11000 !
b11000 7
b11000 >
b11000 E
b11000 L
b11000 M
#15
0"
#16
0#
0&
b101010111100110111101111 4
b101010111100110111101111 9
b101010111100110111101111 /
b101010111100110111101111 G
16
11
b11 W
b101010010011 Q
b101010010011 5
b101010010011 8
b10001 K
b101010010011 U
b101010010011 0
b101010010011 F
b100 P
1"
#17
0"
#18
b101 P
1#
1&
b10011 4
b10011 9
b10011 /
b10011 G
b10011 -
06
01
b110 :
b110 A
b11 H
b111010010011 0
b111010010011 F
b0 I
b10011 .
b10011 O
1"
b110000 !
b110000 7
b110000 >
b110000 E
b110000 L
b110000 M
#19
0"
#20
0#
0&
b101010111100110111101111 4
b101010111100110111101111 9
b101010111100110111101111 /
b101010111100110111101111 G
16
11
b101 W
b10011 Q
b10011 5
b10011 8
b10011 U
b110 P
b101 :
b101 A
b10 H
b10011 0
b10011 F
b100 I
1"
b101000 !
b101000 7
b101000 >
b101000 E
b101000 L
b101000 M
#21
0"
#22
b111 P
1"
#23
0"
#24
b1000 P
1"
#25
0"
#26
b1001 P
1"
#27
0"
#28
b1010 P
1"
#29
0"
#30
b1011 P
b101010111100110111101111 .
b101010111100110111101111 O
1#
1&
1(
1"
1,
#31
0"
#32
b101010111100110111101111 -
b101 W
b101010111100110111101111 Q
b101010111100110111101111 5
b101010111100110111101111 8
b101010111100110111101111 U
b101010111100110111101111 0
b101010111100110111101111 F
b1100 P
1"
#33
0"
#34
b1101 P
b101010111100110111101111 U
b101 W
b101010111100110111101111 Q
1"
#35
0"
#36
b101 W
b101010111100110111101111 Q
b101010111100110111101111 U
b1110 P
1"
#37
0"
#38
b1111 P
b101010111100110111101111 U
b101 W
b101010111100110111101111 Q
1"
#39
0"
#40
b101 W
b101010111100110111101111 Q
b101010111100110111101111 U
b10000 P
0#
0&
0(
1"
0,
#41
0"
#42
b10001 P
1"
#43
0"
#44
b10010 P
1"
#45
0"
#46
b10011 P
1"
#47
0"
#48
b10100 P
1"
#49
0"
#50
01
06
b0 P
b0 K
b0 =
1"
1*
