hardware/src/bsram.v
/** @module : BSRAM
 *  @author : Adaptive & Secure Computing Systems (ASCS) Laboratory
 
 *  Copyright (c) 2018 BRISC-V (ASCS/ECE/BU)
 *  Permission is hereby granted, free of charge, to any person obtaining a copy
 *  of this software and associated documentation files (the "Software"), to deal
 *  in the Software without restriction, including without limitation the rights
 *  to use, copy, modify, merge, publish, distribute, sublicense, and/or sell
 *  copies of the Software, and to permit persons to whom the Software is
 *  furnished to do so, subject to the following conditions:
 *  The above copyright notice and this permission notice shall be included in
 *  all copies or substantial portions of the Software.

 *  THE SOFTWARE IS PROVIDED "AS IS", WITHOUT WARRANTY OF ANY KIND, EXPRESS OR
 *  IMPLIED, INCLUDING BUT NOT LIMITED TO THE WARRANTIES OF MERCHANTABILITY,
 *  FITNESS FOR A PARTICULAR PURPOSE AND NONINFRINGEMENT. IN NO EVENT SHALL THE
 *  AUTHORS OR COPYRIGHT HOLDERS BE LIABLE FOR ANY CLAIM, DAMAGES OR OTHER
 *  LIABILITY, WHETHER IN AN ACTION OF CONTRACT, TORT OR OTHERWISE, ARISING FROM,
 *  OUT OF OR IN CONNECTION WITH THE SOFTWARE OR THE USE OR OTHER DEALINGS IN
 *  THE SOFTWARE.
 */
 
//Same cycle read memory access 

 (* ram_style = "block" *)
module BSRAM #(parameter CORE = 0, DATA_WIDTH = 32, ADDR_WIDTH = 8) (
        clock,
        reset,
        readEnable,
        readAddress,
        readData,
        writeEnable,
        writeAddress,
        writeData, 
        report
); 

localparam MEM_DEPTH = 1 << ADDR_WIDTH;

input clock; 
input reset; 
input readEnable;
input [ADDR_WIDTH-1:0]   readAddress;
output [DATA_WIDTH-1:0]  readData;
input writeEnable;
input [ADDR_WIDTH-1:0]   writeAddress;
input [DATA_WIDTH-1:0]   writeData;
input report; 
 
wire [DATA_WIDTH-1:0]     readData;
reg  [DATA_WIDTH-1:0]     sram [0:MEM_DEPTH-1];
 
//--------------Code Starts Here------------------ 
assign readData = (readEnable & writeEnable & (readAddress == writeAddress))? 
                  writeData : readEnable? sram[readAddress] : 0;

initial begin
    $readmemh("program.vmh", sram);
end

always@(posedge clock) begin : RAM_WRITE
    if(writeEnable)
        sram[writeAddress] <= writeData;
end

reg [31: 0] cycles; 
always @ (posedge clock) begin 
    cycles <= reset? 0 : cycles + 1; 
    if (report)begin
        $display ("------ Core %d SBRAM Unit - Current Cycle %d --------", CORE, cycles); 
        $display ("| Read        [%b]", readEnable);
        $display ("| Read Address[%h]", readAddress);
        $display ("| Read Data   [%h]", readData);
        $display ("| Write       [%b]", writeEnable);
        $display ("| Write Addres[%h]", writeAddress);
        $display ("| Write Data  [%h]", writeData);
        $display ("----------------------------------------------------------------------");
    end 
 end    

endmodule

hardware/src/Cache.v
//////////////////////////////////////////////////////////////////////////////////
// 
//	GENERIC DIRECT-MAPPED CACHE MODEL WITH WRITE-THROUGH AND NO-WRITE-ALLOCATE
// 
//////////////////////////////////////////////////////////////////////////////////

// TODO: should have different read and write inputs for consistency?

module Cache #(
	parameter LOG_NUM_LINES = 2,		// number of lines (entries) in cache
	parameter LOG_NUM_BLOCKS = 1,		// number of blocks in each cache line
	parameter DATA_WIDTH = 32,
	parameter ADDR_WIDTH = 8)(
	input 						clk,
	input 						rst,
	input 						write_en,
	input 	[DATA_WIDTH-1:0]	write_data,
	input 	[ADDR_WIDTH-1:0] 	address,
	output						hit,
	output	[DATA_WIDTH-1:0]	read_data
);

	localparam NUM_TAG_BITS = DATA_WIDTH-LOG_NUM_LINES-LOG_NUM_BLOCKS;
	localparam NUM_LINES = 2**LOG_NUM_LINES;
	localparam NUM_BLOCKS = 2**LOG_NUM_BLOCKS;

	// valid bits of all data in cache
	reg valid[0:NUM_LINES-1];
	
	// tags of all data in cache
	reg [NUM_TAG_BITS-1:0] tags[0:NUM_LINES-1];

	// actual cache storage. each cache line is of size (data width) * (num blocks)
	reg [DATA_WIDTH-1:0] cachemem[0:NUM_LINES-1][0:NUM_BLOCKS-1];

	// index, tag, block offset bits in requested address
	wire [NUM_TAG_BITS-1:0] tag = address[ADDR_WIDTH-1:ADDR_WIDTH-NUM_TAG_BITS];
	wire [LOG_NUM_BLOCKS-1:0] block_offset = address[LOG_NUM_BLOCKS-1:0];
	wire [LOG_NUM_LINES-1:0] index = address[LOG_NUM_LINES+LOG_NUM_BLOCKS-1:LOG_NUM_BLOCKS];

	// does this cache have the requested data
	assign hit = valid[index] && tags[index]==tag;

	// asynchronous read
	assign read_data = cachemem[index][block_offset];

	integer i;
	always @ (posedge clk) begin

		if (rst) begin

			for (i = 0; i < NUM_LINES; i=i+1) begin
				valid[i] <= 1'b0;
			end
		
		end // if (rst)

		else if (write_en) begin

			cachemem[index][block_offset] = write_data;
			valid[index] <= 1'b1;
		
		end // if (write_en)

	end // always @ (posedge clk)

endmodule

hardware/src/CacheModel.v
//////////////////////////////////////////////////////////////////////////////////
// 
//	SIMULATES L1,L2 CACHE AND MAIN MEMORY ALL WORKING TOGETHER
// 
//////////////////////////////////////////////////////////////////////////////////

// TODO: i-cache

module CacheModel #(parameter CORE = 0, DATA_WIDTH = 32, ADDR_WIDTH = 8)(
	input 						clk,			// clock
	input 						rst,			// synchronous reset active high
	input 						report,			// report stats active high
	input 						write_en,
	input	[ADDR_WIDTH-1:0]	address,
	input	[DATA_WIDTH-1:0]	write_data,
	output	[DATA_WIDTH-1:0]	read_data
);


///////////////////////////////////// L1 CACHE /////////////////////////////////////
	
	wire 						l1i_hit, l1d_hit;
	wire 	[DATA_WIDTH-1:0]	l1i_read_data, l1d_read_data;

	Cache l1icache (
		.clk       (clk),
		.rst       (rst),
		.write_en  (write_en),
		.write_data(l1i_write_data),
		.address   (address),
		.hit       (l1i_hit),
		.read_data (l1i_read_data)
	);

	Cache l1dcache (
		.clk       (clk),
		.rst       (rst),
		.write_en  (write_en),
		.write_data(l1d_write_data),
		.address   (address),
		.hit       (l1d_hit),
		.read_data (l1d_read_data)
	);


///////////////////////////////////// L2 CACHE /////////////////////////////////////

	wire 						l2_hit;
	wire 	[DATA_WIDTH-1:0]	l2_read_data;

	Cache l2cache (
		.clk       (clk),
		.rst       (rst),
		.write_en  (write_en),
		.write_data(l2_write_data),
		.address   (address),
		.hit       (l2_hit),
		.read_data (l2_read_data)
	);


///////////////////////////////////// MAIN MEMORY /////////////////////////////////////

	wire 						mm_read_en = 1;
	wire 	[DATA_WIDTH-1:0]	mm_read_data;

	BSRAM main_memory (
		.clock       (clk),
		.reset       (rst),
		.readEnable  (mm_read_en),
		.readAddress (address),
		.readData    (mm_read_data),
		.writeEnable (write_en),
		.writeAddress(address),
		.writeData   (write_data),
		.report      (report)
	);


////////////////////////////////////// READS //////////////////////////////////////

	// In this simulation, all caches and mem can be read at the same time but
	// this is not realistic and impossible in real workd
	assign read_data = l1d_hit	?	l1d_read_data
					 : l2_hit	?	l2_read_data
					 : mm_read_data;


///////////////////////////////////// WRITES /////////////////////////////////////

	// write through all levels of memory whenever write requested or read miss
	assign l1d_write_en = write_en || ~l1d_hit;
	assign l2_write_en = write_en || ~l2_hit;
	assign mm_write_en = write_en;

	// in write req, write the input data. in read miss, write data from lower level of memory
	assign l1d_write_data = ~l1d_hit ? ( ~l2_hit ? mm_read_data : l2_read_data)
						  : write_data;

	assign l2_write_data = ~l2_hit ? mm_read_data : write_data;

endmodule

hardware/testbeds/tb_CacheModel.v
module tb_CacheModel;

	// Inputs
	reg 		clk;
	reg 		rst;
	reg 		report;
	reg 		write_en;
	reg	[7:0]	address;
	reg	[31:0]	write_data;

	// Outputs
	wire [31:0] read_data;

	CacheModel uut (
		.clk       (clk),
		.rst       (rst),
		.report    (report),
		.write_en  (write_en),
		.address   (address),
		.write_data(write_data),
		.read_data (read_data)
	);

	// clock generator
	always #1 clk = ~clk;

	initial begin

		$dumpfile("CacheModel.vcd");
		$dumpvars(0, uut, uut.l1dcache.cachemem[0][0], uut.l1dcache.cachemem[0][1]);

		clk = 1;
		rst = 1;
		report = 0;
		write_en = 0;
		address = 8'h20;
		write_data = 32'habcdef;

		#10 rst = 0;

		write_en = 1;

		#4;
		$finish;

	end // initial

endmodule

hardware/src/CacheModel.vcd
$date
	Thu Apr 19 00:27:19 2018
$end
$version
	Icarus Verilog
$end
$timescale
	1s
$end
$scope module tb_CacheModel $end
$scope module uut $end
$var wire 8 ! address [7:0] $end
$var wire 1 " clk $end
$var wire 1 # l1d_write_en $end
$var wire 1 $ l2_write_en $end
$var wire 1 % mm_read_en $end
$var wire 1 & mm_write_en $end
$var wire 1 ' report $end
$var wire 1 ( rst $end
$var wire 32 ) write_data [31:0] $end
$var wire 1 * write_en $end
$var wire 32 + read_data [31:0] $end
$var wire 32 , mm_read_data [31:0] $end
$var wire 32 - l2_read_data [31:0] $end
$var wire 1 . l2_hit $end
$var wire 32 / l1i_read_data [31:0] $end
$var wire 1 0 l1i_hit $end
$var wire 32 1 l1d_read_data [31:0] $end
$var wire 1 2 l1d_hit $end
$scope module l1dcache $end
$var wire 8 3 address [7:0] $end
$var wire 1 " clk $end
$var wire 1 2 hit $end
$var wire 32 4 read_data [31:0] $end
$var wire 1 ( rst $end
$var wire 32 5 write_data [31:0] $end
$var wire 1 * write_en $end
$var wire 29 6 tag [28:0] $end
$var wire 2 7 index [1:0] $end
$var wire 1 8 block_offset $end
$var integer 32 9 i [31:0] $end
$upscope $end
$scope module l1icache $end
$var wire 8 : address [7:0] $end
$var wire 1 " clk $end
$var wire 1 0 hit $end
$var wire 32 ; read_data [31:0] $end
$var wire 1 ( rst $end
$var wire 32 < write_data [31:0] $end
$var wire 1 * write_en $end
$var wire 29 = tag [28:0] $end
$var wire 2 > index [1:0] $end
$var wire 1 ? block_offset $end
$var integer 32 @ i [31:0] $end
$upscope $end
$scope module l2cache $end
$var wire 8 A address [7:0] $end
$var wire 1 " clk $end
$var wire 1 . hit $end
$var wire 32 B read_data [31:0] $end
$var wire 1 ( rst $end
$var wire 32 C write_data [31:0] $end
$var wire 1 * write_en $end
$var wire 29 D tag [28:0] $end
$var wire 2 E index [1:0] $end
$var wire 1 F block_offset $end
$var integer 32 G i [31:0] $end
$upscope $end
$scope module main_memory $end
$var wire 1 " clock $end
$var wire 8 H readAddress [7:0] $end
$var wire 1 % readEnable $end
$var wire 1 ' report $end
$var wire 1 ( reset $end
$var wire 8 I writeAddress [7:0] $end
$var wire 32 J writeData [31:0] $end
$var wire 1 * writeEnable $end
$var wire 32 K readData [31:0] $end
$var reg 32 L cycles [31:0] $end
$scope begin RAM_WRITE $end
$upscope $end
$upscope $end
$upscope $end
$upscope $end
$scope module tb_CacheModel $end
$scope module uut $end
$scope module l1dcache $end
$var reg 32 M \cachemem[0] [31:0] $end
$upscope $end
$upscope $end
$upscope $end
$scope module tb_CacheModel $end
$scope module uut $end
$scope module l1dcache $end
$var reg 32 N \cachemem[1] [31:0] $end
$upscope $end
$upscope $end
$upscope $end
$enddefinitions $end
#0
$dumpvars
bx N
bx M
b0 L
b111010010011 K
b101010111100110111101111 J
b100000 I
b100000 H
b100 G
0F
b0 E
b100000xxxxxxxxxxxxxxxxxxxxx D
b101010111100110111101111 C
bx B
b100000 A
b100 @
0?
b0 >
b100000xxxxxxxxxxxxxxxxxxxxx =
b101010111100110111101111 <
bx ;
b100000 :
b100 9
08
b0 7
b100000xxxxxxxxxxxxxxxxxxxxx 6
b101010111100110111101111 5
bx 4
b100000 3
02
bx 1
00
bx /
0.
bx -
b111010010011 ,
b111010010011 +
0*
b101010111100110111101111 )
1(
0'
0&
1%
0$
0#
1"
b100000 !
$end
#1
0"
#2
b100 G
b100 9
b100 @
1"
#3
0"
#4
b100 @
b100 9
b100 G
1"
#5
0"
#6
b100 G
b100 9
b100 @
1"
#7
0"
#8
b100 @
b100 9
b100 G
1"
#9
0"
#10
x.
x2
x0
b1 L
b101010111100110111101111 +
b101010111100110111101111 ,
b101010111100110111101111 K
b101010111100110111101111 -
b101010111100110111101111 B
b101010111100110111101111 M
b101010111100110111101111 1
b101010111100110111101111 4
b101010111100110111101111 /
b101010111100110111101111 ;
1"
1#
1$
1&
1*
0(
#11
0"
#12
b10 L
b101010111100110111101111 M
1"
#13
0"
#14
b11 L
b101010111100110111101111 M
1"
